statstruk/__init__.py
statstruk/__main__.py
statstruk/py.typed
statstruk/ratemodel.py
statstruk/ssbmodel.py
ssb_statstruk-0.0.9.dist-info/LICENSE
ssb_statstruk-0.0.9.dist-info/METADATA
ssb_statstruk-0.0.9.dist-info/WHEEL
ssb_statstruk-0.0.9.dist-info/entry_points.txt
ssb_statstruk-0.0.9.dist-info/RECORD
