Metadata-Version: 2.1
Name: ssb-statstruk
Version: 0.0.9
Summary: SSB Statstruk
Home-page: https://github.com/statisticsnorway/ssb-statstruk
License: MIT
Author: Susie Jentoft
Author-email: coo@ssb.no
Requires-Python: >=3.10,<4
Classifier: Development Status :: 4 - Beta
Classifier: License :: OSI Approved :: MIT License
Classifier: Programming Language :: Python :: 3
Classifier: Programming Language :: Python :: 3.10
Classifier: Programming Language :: Python :: 3.11
Classifier: Programming Language :: Python :: 3.12
Requires-Dist: click (>=8.0.1)
Requires-Dist: numpy (>=2.0.0)
Requires-Dist: pandas (>=1.5.3)
Requires-Dist: pandas-stubs (>=2.1.1.230928)
Requires-Dist: poetry-plugin-export (>=1.8.0)
Requires-Dist: statsmodels (>=0.14.1)
Project-URL: Changelog, https://github.com/statisticsnorway/ssb-statstruk/releases
Project-URL: Documentation, https://statisticsnorway.github.io/ssb-statstruk
Project-URL: Repository, https://github.com/statisticsnorway/ssb-statstruk
